frostiiapi/__init__.py
frostii_api-0.1.3.dist-info/METADATA
frostii_api-0.1.3.dist-info/WHEEL
frostii_api-0.1.3.dist-info/top_level.txt
frostii_api-0.1.3.dist-info/RECORD
