Metadata-Version: 2.1
Name: frostii-api
Version: 0.1.3
Summary: An API wrapper for frostii api.
Home-page: UNKNOWN
Author: Alex Hutz
Author-email: frostiiweeb@gmail.com
License: MIT
Keywords: image,image api
Platform: UNKNOWN
Classifier: Development Status :: 3 - Alpha
Classifier: Intended Audience :: Developers
Classifier: License :: OSI Approved :: MIT License
Classifier: Programming Language :: Python :: 3.5
Classifier: Programming Language :: Python :: 3.6
Classifier: Programming Language :: Python :: 3.7
Classifier: Programming Language :: Python :: 3.8
Classifier: Programming Language :: Python :: 3.9
Requires-Python: >=3.5.3
Requires-Dist: aiohttp (>=3.7.3)
